NLP/NLP 1/1-Prereqs.py
NLP/NLP 1/2-Chi2test.py
NLP/NLP 1/2-T-test.py
NLP/NLP 1/3-WSD-nb.py
NLP/NLP 1/4-Hindle-Rooth.py
NLP/NLP 1/5-HMM-Trellis.py
NLP/NLP 1/6-HMM-Viterbi.py
NLP/NLP 1/7-PCFG-parsetree.py
"NLP/NLP 2/Lab11(Viterbi-PCFG,Machine-translation)/corpora_tools.py"
"NLP/NLP 2/Lab11(Viterbi-PCFG,Machine-translation)/data_utils.py"
"NLP/NLP 2/Lab11(Viterbi-PCFG,Machine-translation)/train_translator.py"
sciklt/README.md
sciklt/__init__.py
sciklt/licence.txt
sciklt/main.py
sciklt/data/NLP/NLP 1/1-Prereqs.py
sciklt/data/NLP/NLP 1/2-Chi2test.py
sciklt/data/NLP/NLP 1/2-T-test.py
sciklt/data/NLP/NLP 1/3-WSD-nb.py
sciklt/data/NLP/NLP 1/4-Hindle-Rooth.py
sciklt/data/NLP/NLP 1/5-HMM-Trellis.py
sciklt/data/NLP/NLP 1/6-HMM-Viterbi.py
sciklt/data/NLP/NLP 1/7-PCFG-parsetree.py
sciklt/data/NLP/NLP 1/Chi2test.ipynb
sciklt/data/NLP/NLP 1/Hindle-Rooth.ipynb
sciklt/data/NLP/NLP 1/Lab 10 - Text generator using LSTM.ipynb
sciklt/data/NLP/NLP 1/Lab 11 NMT.ipynb
sciklt/data/NLP/NLP 1/PCFG.ipynb
sciklt/data/NLP/NLP 1/Prereqs.ipynb
sciklt/data/NLP/NLP 1/T test.ipynb
sciklt/data/NLP/NLP 1/TFIDF BOW.ipynb
sciklt/data/NLP/NLP 1/Trellis.ipynb
sciklt/data/NLP/NLP 1/WSD.ipynb
sciklt/data/NLP/NLP 1/Word2Vec.ipynb
sciklt/data/NLP/NLP 2/Lab01(tokenizer)/tokenizer.ipynb
sciklt/data/NLP/NLP 2/Lab01(tokenizer)/training_tokenizer.txt
sciklt/data/NLP/NLP 2/Lab02(stemming)/exp0.ipynb
sciklt/data/NLP/NLP 2/Lab02(stemming)/lab2.ipynb
sciklt/data/NLP/NLP 2/Lab02(stemming)/test.txt
sciklt/data/NLP/NLP 2/Lab02(stemming)/tokenizing.ipynb
sciklt/data/NLP/NLP 2/Lab03(parse-tree)/collocation.ipynb
sciklt/data/NLP/NLP 2/Lab03(parse-tree)/lab3.ipynb
sciklt/data/NLP/NLP 2/Lab03(parse-tree)/nlp.txt
sciklt/data/NLP/NLP 2/Lab04(collocation)/Lab4-NLP-Exp-2.ipynb
sciklt/data/NLP/NLP 2/Lab04(collocation)/collocation.ipynb
sciklt/data/NLP/NLP 2/Lab05(WSD)/NLP-Lab-5-Exp3.ipynb
sciklt/data/NLP/NLP 2/Lab05(WSD)/word-sense-disambiguation.ipynb
sciklt/data/NLP/NLP 2/Lab06(additional-exercise)/lab6.ipynb
sciklt-4.0.dist-info/METADATA
sciklt-4.0.dist-info/WHEEL
sciklt-4.0.dist-info/top_level.txt
sciklt-4.0.dist-info/RECORD
