Metadata-Version: 2.1
Name: sciklt
Version: 4.0
Summary: Dependency for ML based modules
Author: Anonymus
